{"v":"5.6.5","fr":60,"ip":0,"op":120,"w":512,"h":512,"nm":"Komp 1","ddd":1,"assets":[],"layers":[{"ddd":1,"ind":1,"ty":4,"nm":"Ebene 1/mts-logo Konturen","sr":1,"ks":{"o":{"a":1,"k":[{"i":{"x":[0.667],"y":[1]},"o":{"x":[0.167],"y":[0.167]},"t":0,"s":[0]},{"t":60,"s":[100]}],"ix":11},"rx":{"a":0,"k":0,"ix":8},"ry":{"a":1,"k":[{"i":{"x":[0.667],"y":[1]},"o":{"x":[0.167],"y":[0]},"t":0,"s":[0]},{"t":60,"s":[0]}],"ix":9},"rz":{"a":1,"k":[{"i":{"x":[0.667],"y":[1]},"o":{"x":[0.167],"y":[0.167]},"t":0,"s":[90]},{"t":60,"s":[0]}],"ix":10},"or":{"a":1,"k":[{"i":{"x":0.667,"y":1},"o":{"x":0.167,"y":0.002},"t":0,"s":[90,0,0],"to":[0,0,0],"ti":[0,0,0]},{"t":60,"s":[0,0,0]}],"ix":7},"p":{"a":1,"k":[{"i":{"x":0.667,"y":1},"o":{"x":0.167,"y":0.167},"t":0,"s":[256,0,512],"to":[0,42.667,-85.333],"ti":[0,-42.667,85.333]},{"t":60,"s":[256,256,0]}],"ix":2},"a":{"a":0,"k":[138.5,240.5,0],"ix":1},"s":{"a":1,"k":[{"i":{"x":[0.667,0.667,0.667],"y":[1,1,1]},"o":{"x":[0.167,0.167,0.167],"y":[0.167,0.167,0.167]},"t":0,"s":[10,10,10]},{"t":60,"s":[90,90,90]}],"ix":6}},"ao":0,"shapes":[{"ty":"gr","it":[{"ind":0,"ty":"sh","ix":1,"ks":{"a":0,"k":{"i":[[0,0],[0,0],[0.259,-0.193],[0.371,-0.053],[0.338,0.107],[0.195,0.227],[0,0],[0,0],[0.272,-0.107],[0.314,0],[0.333,0.201],[0.074,0.32],[0,0],[0,0],[0,0],[0,0],[-0.274,0.107],[-0.315,0],[-0.269,-0.108],[-0.175,-0.193],[0,0],[0,0]],"o":[[0,0],[-0.075,0.267],[-0.259,0.194],[-0.378,0.047],[-0.339,-0.107],[0,0],[0,0],[-0.157,0.193],[-0.274,0.107],[-0.435,0],[-0.334,-0.2],[0,0],[0,0],[0,0],[0,0],[0.158,-0.193],[0.272,-0.108],[0.314,0],[0.268,0.107],[0,0],[0,0],[0,0]],"v":[[13.267,-7.289],[9.935,6.181],[9.435,6.872],[8.49,7.243],[7.415,7.153],[6.616,6.652],[0.007,-1.186],[-6.616,6.652],[-7.261,7.103],[-8.143,7.263],[-9.296,6.962],[-9.907,6.181],[-13.267,-7.289],[-9.602,-7.289],[-7.213,2.202],[-1.521,-4.353],[-0.874,-4.803],[0.007,-4.964],[0.882,-4.803],[1.548,-4.353],[7.214,2.202],[9.602,-7.289]],"c":true},"ix":2},"nm":"Pfad 1","mn":"ADBE Vector Shape - Group","hd":false},{"ty":"fl","c":{"a":0,"k":[0.988235353956,0.980392216701,0.945098099054,1],"ix":4},"o":{"a":0,"k":100,"ix":5},"r":1,"bm":0,"nm":"Fläche 1","mn":"ADBE Vector Graphic - Fill","hd":false},{"ty":"tr","p":{"a":0,"k":[245.067,472.968],"ix":2},"a":{"a":0,"k":[0,0],"ix":1},"s":{"a":0,"k":[100,100],"ix":3},"r":{"a":0,"k":0,"ix":6},"o":{"a":0,"k":100,"ix":7},"sk":{"a":0,"k":0,"ix":4},"sa":{"a":0,"k":0,"ix":5},"nm":"Transformieren"}],"nm":"Gruppe 1","np":2,"cix":2,"bm":0,"ix":1,"mn":"ADBE Vector Group","hd":false},{"ty":"gr","it":[{"ind":0,"ty":"sh","ix":1,"ks":{"a":0,"k":{"i":[[0,0],[0,0],[0,0],[0,0],[0.356,-0.023],[0.467,-0.093],[0.519,-0.193],[0.435,-0.341],[0.282,-0.512],[0,-0.729]],"o":[[0,0],[0,0],[0,0],[-0.11,0],[-0.356,0.023],[-0.468,0.093],[-0.518,0.193],[-0.435,0.341],[-0.283,0.511],[0,0]],"v":[[-6.345,1.052],[6.345,1.052],[6.345,-4.58],[-0.001,-4.58],[-0.702,-4.545],[-1.936,-4.37],[-3.417,-3.939],[-4.846,-3.137],[-5.922,-1.859],[-6.345,0]],"c":true},"ix":2},"nm":"Pfad 1","mn":"ADBE Vector Shape - Group","hd":false},{"ind":1,"ty":"sh","ix":2,"ks":{"a":0,"k":{"i":[[0,0],[0,0],[0,0],[0,0],[0,0],[0,0],[0,0],[-0.5,0.882],[-0.888,0.635],[-1.212,0.354],[-1.434,0],[0,0],[-0.223,-0.067],[-0.168,-0.121],[-0.092,-0.161],[0,-0.181]],"o":[[0,0],[0,0],[0,0],[0,0],[0,0],[0,0],[0,-1.05],[0.5,-0.882],[0.889,-0.634],[1.213,-0.354],[0,0],[0.25,0],[0.221,0.067],[0.166,0.12],[0.093,0.16],[0,0]],"v":[[9.956,7.186],[6.345,7.186],[6.345,3.658],[-6.345,3.658],[-6.345,7.186],[-9.956,7.186],[-9.956,0],[-9.206,-2.897],[-7.124,-5.172],[-3.971,-6.655],[-0.001,-7.186],[8.137,-7.186],[8.845,-7.086],[9.428,-6.805],[9.816,-6.384],[9.956,-5.873]],"c":true},"ix":2},"nm":"Pfad 2","mn":"ADBE Vector Shape - Group","hd":false},{"ty":"mm","mm":1,"nm":"Pfade zusammenführen 1","mn":"ADBE Vector Filter - Merge","hd":false},{"ty":"fl","c":{"a":0,"k":[0.988235353956,0.980392216701,0.945098099054,1],"ix":4},"o":{"a":0,"k":100,"ix":5},"r":1,"bm":0,"nm":"Fläche 1","mn":"ADBE Vector Graphic - Fill","hd":false},{"ty":"tr","p":{"a":0,"k":[214.497,472.864],"ix":2},"a":{"a":0,"k":[0,0],"ix":1},"s":{"a":0,"k":[100,100],"ix":3},"r":{"a":0,"k":0,"ix":6},"o":{"a":0,"k":100,"ix":7},"sk":{"a":0,"k":0,"ix":4},"sa":{"a":0,"k":0,"ix":5},"nm":"Transformieren"}],"nm":"Gruppe 2","np":4,"cix":2,"bm":0,"ix":2,"mn":"ADBE Vector Group","hd":false},{"ty":"gr","it":[{"ind":0,"ty":"sh","ix":1,"ks":{"a":0,"k":{"i":[[0,0],[0,0],[0,0],[0,0],[0.283,-0.107],[0.324,0],[0.273,0.107],[0.157,0.208],[0,0],[0,0],[0,0],[0,0],[-0.246,0.233],[-0.398,0.08],[-0.194,-0.01],[-0.18,-0.05],[-0.148,-0.09],[-0.102,-0.127],[0,0],[0,0],[-0.374,0.107],[-0.408,-0.073],[-0.25,-0.234],[0,-0.301]],"o":[[0,0],[0,0],[0,0],[-0.158,0.208],[-0.282,0.107],[-0.314,0],[-0.273,-0.107],[0,0],[0,0],[0,0],[0,0],[0,-0.301],[0.245,-0.234],[0.194,-0.033],[0.194,0.01],[0.181,0.05],[0.148,0.091],[0,0],[0,0],[0.213,-0.253],[0.375,-0.107],[0.389,0.08],[0.25,0.233],[0,0]],"v":[[11.587,7.202],[7.949,7.202],[7.949,-1.357],[1.548,6.771],[0.888,7.242],[-0.021,7.402],[-0.903,7.242],[-1.548,6.771],[-7.977,-1.357],[-7.977,7.202],[-11.587,7.202],[-11.587,-6.057],[-11.219,-6.859],[-10.254,-7.329],[-9.671,-7.365],[-9.109,-7.275],[-8.616,-7.065],[-8.241,-6.738],[-0.021,3.574],[8.199,-6.738],[9.08,-7.28],[10.254,-7.329],[11.212,-6.859],[11.587,-6.057]],"c":true},"ix":2},"nm":"Pfad 1","mn":"ADBE Vector Shape - Group","hd":false},{"ty":"fl","c":{"a":0,"k":[0.988235353956,0.980392216701,0.945098099054,1],"ix":4},"o":{"a":0,"k":100,"ix":5},"r":1,"bm":0,"nm":"Fläche 1","mn":"ADBE Vector Graphic - Fill","hd":false},{"ty":"tr","p":{"a":0,"k":[184.871,472.847],"ix":2},"a":{"a":0,"k":[0,0],"ix":1},"s":{"a":0,"k":[100,100],"ix":3},"r":{"a":0,"k":0,"ix":6},"o":{"a":0,"k":100,"ix":7},"sk":{"a":0,"k":0,"ix":4},"sa":{"a":0,"k":0,"ix":5},"nm":"Transformieren"}],"nm":"Gruppe 3","np":2,"cix":2,"bm":0,"ix":3,"mn":"ADBE Vector Group","hd":false},{"ty":"gr","it":[{"ind":0,"ty":"sh","ix":1,"ks":{"a":0,"k":{"i":[[0,0],[0,0],[0,0],[0,0]],"o":[[0,0],[0,0],[0,0],[0,0]],"v":[[7.414,1.313],[-3.985,1.313],[-3.985,-1.313],[7.414,-1.313]],"c":true},"ix":2},"nm":"Pfad 1","mn":"ADBE Vector Shape - Group","hd":false},{"ind":1,"ty":"sh","ix":2,"ks":{"a":0,"k":{"i":[[0,0],[0,0],[0.593,0.127],[0.505,0.29],[0.338,0.464],[0,0.675],[0,0],[-0.092,0.16],[-0.161,0.12],[-0.221,0.067],[-0.26,0],[0,0],[0,0],[0,0],[0,0],[-0.25,-0.18],[-0.482,0],[0,0]],"o":[[0,0],[-0.5,0],[-0.592,-0.127],[-0.504,-0.291],[-0.339,-0.464],[0,0],[0,-0.181],[0.093,-0.161],[0.162,-0.121],[0.223,-0.067],[0,0],[0,0],[0,0],[0,0],[0,0.341],[0.249,0.181],[0,0],[0,0]],"v":[[9.039,7.186],[-3.985,7.186],[-5.624,6.995],[-7.269,6.369],[-8.532,5.236],[-9.039,3.527],[-9.039,-5.873],[-8.901,-6.384],[-8.519,-6.805],[-7.943,-7.086],[-7.22,-7.186],[9.039,-7.186],[9.039,-4.58],[-5.429,-4.58],[-5.429,3.527],[-5.054,4.309],[-3.957,4.58],[9.039,4.58]],"c":true},"ix":2},"nm":"Pfad 2","mn":"ADBE Vector Shape - Group","hd":false},{"ty":"mm","mm":1,"nm":"Pfade zusammenführen 1","mn":"ADBE Vector Filter - Merge","hd":false},{"ty":"fl","c":{"a":0,"k":[0.988235353956,0.980392216701,0.945098099054,1],"ix":4},"o":{"a":0,"k":100,"ix":5},"r":1,"bm":0,"nm":"Fläche 1","mn":"ADBE Vector Graphic - Fill","hd":false},{"ty":"tr","p":{"a":0,"k":[156.495,472.864],"ix":2},"a":{"a":0,"k":[0,0],"ix":1},"s":{"a":0,"k":[100,100],"ix":3},"r":{"a":0,"k":0,"ix":6},"o":{"a":0,"k":100,"ix":7},"sk":{"a":0,"k":0,"ix":4},"sa":{"a":0,"k":0,"ix":5},"nm":"Transformieren"}],"nm":"Gruppe 4","np":4,"cix":2,"bm":0,"ix":4,"mn":"ADBE Vector Group","hd":false},{"ty":"gr","it":[{"ind":0,"ty":"sh","ix":1,"ks":{"a":0,"k":{"i":[[0,0],[0.204,-0.469],[0.347,-0.358],[0.453,-0.253],[0.495,-0.164],[0.505,-0.073],[0.445,0],[0,0],[0,0],[0,0],[0,0],[0,0],[0,0],[-0.375,0.111],[-0.272,0.187],[-0.148,0.264],[0,0.341],[0,0],[0.051,0.077],[0.079,0.037],[0.087,0.007],[0.075,0],[0,0],[0,0],[0,0],[0,0],[-0.093,0.16],[-0.162,0.12],[-0.221,0.067],[-0.26,0],[0,0],[-0.555,-0.21],[-0.347,-0.318],[-0.153,-0.368],[0,-0.32]],"o":[[0,0.594],[-0.203,0.468],[-0.346,0.358],[-0.454,0.254],[-0.496,0.163],[-0.504,0.074],[0,0],[0,0],[0,0],[0,0],[0,0],[0,0],[0.454,-0.027],[0.375,-0.11],[0.273,-0.188],[0.148,-0.264],[0,0],[0,-0.147],[-0.051,-0.078],[-0.079,-0.037],[-0.088,-0.007],[0,0],[0,0],[0,0],[0,0],[0,-0.18],[0.093,-0.16],[0.162,-0.12],[0.223,-0.068],[0,0],[0.806,0],[0.555,0.21],[0.348,0.317],[0.153,0.368],[0,0]],"v":[[9.518,-2.355],[9.212,-0.761],[8.386,0.476],[7.186,1.393],[5.763,2.02],[4.262,2.375],[2.839,2.486],[10.379,7.186],[4.798,7.186],[-2.728,2.486],[-5.325,2.486],[-5.325,-0.12],[2.839,-0.12],[4.082,-0.326],[5.054,-0.771],[5.686,-1.448],[5.908,-2.355],[5.908,-3.999],[5.832,-4.334],[5.637,-4.505],[5.388,-4.57],[5.144,-4.58],[-6.769,-4.58],[-6.769,7.186],[-10.379,7.186],[-10.379,-5.873],[-10.24,-6.384],[-9.858,-6.805],[-9.283,-7.085],[-8.56,-7.186],[5.144,-7.186],[7.186,-6.87],[8.539,-6.078],[9.289,-5.051],[9.518,-4.019]],"c":true},"ix":2},"nm":"Pfad 1","mn":"ADBE Vector Shape - Group","hd":false},{"ty":"fl","c":{"a":0,"k":[0.988235353956,0.980392216701,0.945098099054,1],"ix":4},"o":{"a":0,"k":100,"ix":5},"r":1,"bm":0,"nm":"Fläche 1","mn":"ADBE Vector Graphic - Fill","hd":false},{"ty":"tr","p":{"a":0,"k":[130.13,472.864],"ix":2},"a":{"a":0,"k":[0,0],"ix":1},"s":{"a":0,"k":[100,100],"ix":3},"r":{"a":0,"k":0,"ix":6},"o":{"a":0,"k":100,"ix":7},"sk":{"a":0,"k":0,"ix":4},"sa":{"a":0,"k":0,"ix":5},"nm":"Transformieren"}],"nm":"Gruppe 5","np":2,"cix":2,"bm":0,"ix":5,"mn":"ADBE Vector Group","hd":false},{"ty":"gr","it":[{"ind":0,"ty":"sh","ix":1,"ks":{"a":0,"k":{"i":[[0,0],[0,0],[0,0],[0,0]],"o":[[0,0],[0,0],[0,0],[0,0]],"v":[[1.805,7.186],[-1.805,7.186],[-1.805,-7.186],[1.805,-7.186]],"c":true},"ix":2},"nm":"Pfad 1","mn":"ADBE Vector Shape - Group","hd":false},{"ty":"fl","c":{"a":0,"k":[0.988235353956,0.980392216701,0.945098099054,1],"ix":4},"o":{"a":0,"k":100,"ix":5},"r":1,"bm":0,"nm":"Fläche 1","mn":"ADBE Vector Graphic - Fill","hd":false},{"ty":"tr","p":{"a":0,"k":[109.461,472.864],"ix":2},"a":{"a":0,"k":[0,0],"ix":1},"s":{"a":0,"k":[100,100],"ix":3},"r":{"a":0,"k":0,"ix":6},"o":{"a":0,"k":100,"ix":7},"sk":{"a":0,"k":0,"ix":4},"sa":{"a":0,"k":0,"ix":5},"nm":"Transformieren"}],"nm":"Gruppe 6","np":2,"cix":2,"bm":0,"ix":6,"mn":"ADBE Vector Group","hd":false},{"ty":"gr","it":[{"ind":0,"ty":"sh","ix":1,"ks":{"a":0,"k":{"i":[[0,0],[0,0],[0,0],[0,0]],"o":[[0,0],[0,0],[0,0],[0,0]],"v":[[7.428,1.313],[-3.985,1.313],[-3.985,-1.313],[7.428,-1.313]],"c":true},"ix":2},"nm":"Pfad 1","mn":"ADBE Vector Shape - Group","hd":false},{"ind":1,"ty":"sh","ix":2,"ks":{"a":0,"k":{"i":[[0,0],[0,0],[0,0],[0,0],[0,0],[-0.093,0.16],[-0.162,0.12],[-0.221,0.067],[-0.26,0],[0,0]],"o":[[0,0],[0,0],[0,0],[0,0],[0,-0.181],[0.093,-0.161],[0.162,-0.121],[0.223,-0.067],[0,0],[0,0]],"v":[[9.039,-4.58],[-5.429,-4.58],[-5.429,7.186],[-9.039,7.186],[-9.039,-5.873],[-8.9,-6.384],[-8.518,-6.805],[-7.943,-7.086],[-7.22,-7.186],[9.039,-7.186]],"c":true},"ix":2},"nm":"Pfad 2","mn":"ADBE Vector Shape - Group","hd":false},{"ty":"mm","mm":1,"nm":"Pfade zusammenführen 1","mn":"ADBE Vector Filter - Merge","hd":false},{"ty":"fl","c":{"a":0,"k":[0.988235353956,0.980392216701,0.945098099054,1],"ix":4},"o":{"a":0,"k":100,"ix":5},"r":1,"bm":0,"nm":"Fläche 1","mn":"ADBE Vector Graphic - Fill","hd":false},{"ty":"tr","p":{"a":0,"k":[91.407,472.864],"ix":2},"a":{"a":0,"k":[0,0],"ix":1},"s":{"a":0,"k":[100,100],"ix":3},"r":{"a":0,"k":0,"ix":6},"o":{"a":0,"k":100,"ix":7},"sk":{"a":0,"k":0,"ix":4},"sa":{"a":0,"k":0,"ix":5},"nm":"Transformieren"}],"nm":"Gruppe 7","np":4,"cix":2,"bm":0,"ix":7,"mn":"ADBE Vector Group","hd":false},{"ty":"gr","it":[{"ind":0,"ty":"sh","ix":1,"ks":{"a":0,"k":{"i":[[0,0],[0.092,-0.16],[0.166,-0.117],[0.222,-0.067],[0.251,0],[0,0],[0.787,0.12],[0.735,0.251],[0.648,0.388],[0.487,0.531],[0.278,0.685],[0,0.842],[0,0],[0,0],[0,0],[-0.283,-0.508],[-0.436,-0.341],[-0.519,-0.194],[-0.467,-0.094],[-0.356,-0.023],[-0.111,0],[0,0],[0,0],[0,0]],"o":[[0,0.187],[-0.094,0.161],[-0.167,0.117],[-0.223,0.067],[0,0],[-0.769,0],[-0.787,-0.121],[-0.736,-0.25],[-0.648,-0.388],[-0.486,-0.531],[-0.278,-0.684],[0,0],[0,0],[0,0],[0,0.735],[0.283,0.508],[0.435,0.341],[0.519,0.193],[0.467,0.093],[0.357,0.023],[0,0],[0,0],[0,0],[0,0]],"v":[[9.956,5.873],[9.818,6.394],[9.428,6.81],[8.846,7.086],[8.137,7.186],[0.001,7.186],[-2.333,7.006],[-4.617,6.449],[-6.693,5.492],[-8.394,4.114],[-9.538,2.29],[-9.956,0],[-9.956,-7.186],[-6.346,-7.186],[-6.346,0],[-5.922,1.864],[-4.846,3.137],[-3.415,3.939],[-1.937,4.37],[-0.702,4.545],[0.001,4.58],[6.346,4.58],[6.346,-7.186],[9.956,-7.186]],"c":true},"ix":2},"nm":"Pfad 1","mn":"ADBE Vector Shape - Group","hd":false},{"ty":"fl","c":{"a":0,"k":[0.988235353956,0.980392216701,0.945098099054,1],"ix":4},"o":{"a":0,"k":100,"ix":5},"r":1,"bm":0,"nm":"Fläche 1","mn":"ADBE Vector Graphic - Fill","hd":false},{"ty":"tr","p":{"a":0,"k":[50.441,472.864],"ix":2},"a":{"a":0,"k":[0,0],"ix":1},"s":{"a":0,"k":[100,100],"ix":3},"r":{"a":0,"k":0,"ix":6},"o":{"a":0,"k":100,"ix":7},"sk":{"a":0,"k":0,"ix":4},"sa":{"a":0,"k":0,"ix":5},"nm":"Transformieren"}],"nm":"Gruppe 8","np":2,"cix":2,"bm":0,"ix":8,"mn":"ADBE Vector Group","hd":false},{"ty":"gr","it":[{"ind":0,"ty":"sh","ix":1,"ks":{"a":0,"k":{"i":[[0,0],[0,0],[0,0],[0,0]],"o":[[0,0],[0,0],[0,0],[0,0]],"v":[[7.415,1.313],[-3.984,1.313],[-3.984,-1.313],[7.415,-1.313]],"c":true},"ix":2},"nm":"Pfad 1","mn":"ADBE Vector Shape - Group","hd":false},{"ind":1,"ty":"sh","ix":2,"ks":{"a":0,"k":{"i":[[0,0],[0,0],[0.592,0.127],[0.505,0.29],[0.338,0.464],[0,0.675],[0,0],[-0.093,0.16],[-0.161,0.12],[-0.222,0.067],[-0.259,0],[0,0],[0,0],[0,0],[0,0],[-0.249,-0.18],[-0.483,0],[0,0]],"o":[[0,0],[-0.5,0],[-0.592,-0.127],[-0.504,-0.291],[-0.338,-0.464],[0,0],[0,-0.181],[0.093,-0.161],[0.163,-0.121],[0.222,-0.067],[0,0],[0,0],[0,0],[0,0],[0,0.341],[0.25,0.181],[0,0],[0,0]],"v":[[9.039,7.186],[-3.985,7.186],[-5.623,6.995],[-7.269,6.369],[-8.532,5.236],[-9.039,3.527],[-9.039,-5.873],[-8.9,-6.384],[-8.519,-6.805],[-7.942,-7.086],[-7.22,-7.186],[9.039,-7.186],[9.039,-4.58],[-5.429,-4.58],[-5.429,3.527],[-5.054,4.309],[-3.956,4.58],[9.039,4.58]],"c":true},"ix":2},"nm":"Pfad 2","mn":"ADBE Vector Shape - Group","hd":false},{"ty":"mm","mm":1,"nm":"Pfade zusammenführen 1","mn":"ADBE Vector Filter - Merge","hd":false},{"ty":"fl","c":{"a":0,"k":[0.988235353956,0.980392216701,0.945098099054,1],"ix":4},"o":{"a":0,"k":100,"ix":5},"r":1,"bm":0,"nm":"Fläche 1","mn":"ADBE Vector Graphic - Fill","hd":false},{"ty":"tr","p":{"a":0,"k":[24.098,472.864],"ix":2},"a":{"a":0,"k":[0,0],"ix":1},"s":{"a":0,"k":[100,100],"ix":3},"r":{"a":0,"k":0,"ix":6},"o":{"a":0,"k":100,"ix":7},"sk":{"a":0,"k":0,"ix":4},"sa":{"a":0,"k":0,"ix":5},"nm":"Transformieren"}],"nm":"Gruppe 9","np":4,"cix":2,"bm":0,"ix":9,"mn":"ADBE Vector Group","hd":false},{"ty":"gr","it":[{"ind":0,"ty":"sh","ix":1,"ks":{"a":0,"k":{"i":[[0,0],[-9.274,13.055],[-6.689,4.542],[-7.895,1.609],[-3.988,-0.004],[-0.993,-0.062],[0,0],[-0.99,-0.112],[-0.98,-0.162],[-6.608,-3.982],[-4.887,-6.005],[-2.434,-7.589],[-0.397,-4.017],[0,0],[-0.027,-0.515],[0.007,-1.04],[0.372,-2.062],[5.521,-6.478],[8.204,-2.83],[4.319,-0.316],[1.102,0.013],[0,0],[0.556,0.083],[0,0],[0.548,0.128],[0,0],[3.655,2.586],[2.657,3.539],[1.353,4.148],[-0.196,4.292],[-0.062,0.552],[0,0],[-0.112,0.54],[0,0],[-0.167,0.523],[0,0],[-0.225,0.498],[0,0],[-3.165,2.753],[-3.877,1.149],[-3.802,-0.608],[0,0],[2.941,-1.789],[1.961,-2.608],[0.794,-3.003],[0,0],[0.07,-0.376],[0,0],[0.03,-0.379],[0,0],[-0.005,-0.378],[0,0],[-0.042,-0.386],[-0.171,-0.763],[0,0],[-0.68,-1.376],[0,0],[-0.182,-0.334],[0,0],[0,0],[0,0],[0,0],[0,0],[-5.715,-1.244],[0,0],[-0.36,-0.06],[0,0],[-0.369,0.006],[0,0],[-0.381,0.004],[-0.384,0.035],[-0.763,0.109],[-0.382,0.053],[0,0],[-0.761,0.134],[-0.733,0.246],[-4.46,4.483],[-1.854,6.204],[-0.22,0.787],[-0.139,0.808],[-0.073,0.823],[-0.037,0.419],[0,0],[0.493,3.43],[4.112,5.814],[6.322,3.281],[6.935,-0.078],[0.862,-0.045],[0.86,-0.087],[0,0],[0.852,-0.143],[3.236,-1.041],[1.57,-0.63],[0.386,-0.17],[0.39,-0.16],[0.753,-0.382],[2.847,-1.816],[4.481,-5.178],[1.889,-2.907],[0,0],[0.445,-0.754],[0.407,-0.778],[0,0],[0,0],[1.414,-7.334]],"o":[[-2.657,-15.017],[4.574,-6.583],[6.641,-4.629],[3.958,-0.78],[0.998,0.023],[0,0],[0.993,0.088],[0.99,0.141],[7.84,1.493],[6.609,3.995],[4.871,6.001],[1.222,3.787],[0,0],[0.038,0.508],[0.067,1.033],[-0.078,2.075],[-1.334,8.303],[-5.557,6.453],[-4.077,1.476],[-1.085,0.072],[0,0],[-0.562,-0.014],[0,0],[-0.554,-0.096],[0,0],[-4.333,-1.172],[-3.682,-2.528],[-2.694,-3.515],[-1.314,-4.163],[0.019,-0.54],[0,0],[0.071,-0.547],[0,0],[0.129,-0.534],[0,0],[0.183,-0.515],[0,0],[1.824,-3.935],[3.166,-2.751],[3.878,-1.148],[0,0],[-3.619,0.616],[-2.946,1.771],[-1.967,2.601],[0,0],[-0.107,0.369],[0,0],[-0.06,0.377],[0,0],[-0.021,0.377],[0,0],[0.005,0.373],[0.124,0.778],[0,0],[0.471,1.475],[0,0],[0.165,0.343],[0,0],[0,0],[0,0],[0,0],[0,0],[4.056,4.418],[0,0],[0.355,0.085],[0,0],[0.361,0.056],[0,0],[0.366,0.022],[0.386,-0.012],[0.768,-0.057],[0.382,-0.046],[0,0],[0.764,-0.11],[0.741,-0.207],[5.927,-1.737],[4.424,-4.517],[0.256,-0.772],[0.178,-0.794],[0.126,-0.809],[0.045,-0.411],[0,0],[0.195,-3.397],[-0.994,-6.844],[-4.074,-5.823],[-6.314,-3.307],[-0.87,0.031],[-0.864,0.075],[0,0],[-0.861,0.109],[-3.4,0.65],[-1.608,0.562],[-0.393,0.157],[-0.386,0.174],[-0.779,0.325],[-3.052,1.426],[-5.684,3.633],[-2.24,2.586],[0,0],[-0.456,0.742],[-0.455,0.75],[0,0],[0,0],[-3.029,6.388],[0,0]],"v":[[-62.184,17.491],[-51.532,-27.12],[-34.401,-43.974],[-12.211,-53.386],[-0.245,-54.519],[2.74,-54.454],[5.708,-54.262],[8.692,-53.93],[11.646,-53.446],[33.434,-44.969],[50.836,-29.901],[62.067,-9.392],[64.544,2.358],[64.693,3.868],[64.774,5.411],[64.812,8.52],[64.202,14.747],[53.442,37.408],[32.416,51.83],[19.709,54.418],[16.453,54.51],[13.09,54.333],[11.417,54.14],[9.749,53.882],[8.087,53.594],[6.456,53.157],[-5.731,47.604],[-15.336,38.444],[-21.337,26.757],[-23.143,13.941],[-23.092,12.328],[-22.915,10.68],[-22.703,9.045],[-22.35,7.431],[-21.964,5.835],[-21.454,4.275],[-20.909,2.736],[-20.243,1.248],[-12.623,-8.916],[-1.892,-14.86],[9.83,-15.675],[9.83,-14.306],[-0.116,-10.701],[-7.548,-4.044],[-11.723,4.475],[-12.014,5.599],[-12.212,6.739],[-12.395,7.873],[-12.472,9.019],[-12.539,10.156],[-12.51,11.295],[-12.474,12.426],[-12.334,13.591],[-11.993,15.914],[-11.474,18.184],[-9.885,22.508],[-9.431,23.555],[-8.875,24.555],[-8.319,25.548],[-8.045,26.044],[-7.716,26.509],[-6.423,28.367],[-4.977,30.099],[10.042,38.988],[11.105,39.243],[12.187,39.412],[13.269,39.574],[14.357,39.696],[16.551,39.8],[17.698,39.78],[18.856,39.754],[21.16,39.57],[22.308,39.437],[23.447,39.247],[25.717,38.805],[27.953,38.207],[43.878,28.699],[53.459,12.325],[54.104,9.973],[54.599,7.571],[54.963,5.127],[55.102,3.889],[55.18,2.617],[54.778,-7.658],[47.163,-27.122],[31.27,-41.122],[10.909,-45.932],[8.314,-45.847],[5.736,-45.633],[3.141,-45.301],[0.575,-44.861],[-9.385,-42.327],[-14.166,-40.594],[-15.344,-40.13],[-16.506,-39.625],[-18.819,-38.602],[-27.712,-33.803],[-43.117,-20.58],[-49.343,-12.349],[-50.721,-10.139],[-52.013,-7.868],[-53.242,-5.549],[-53.841,-4.374],[-54.389,-3.175],[-60.816,17.491]],"c":true},"ix":2},"nm":"Pfad 1","mn":"ADBE Vector Shape - Group","hd":false},{"ty":"fl","c":{"a":0,"k":[0.988235353956,0.980392216701,0.945098099054,1],"ix":4},"o":{"a":0,"k":100,"ix":5},"r":1,"bm":0,"nm":"Fläche 1","mn":"ADBE Vector Graphic - Fill","hd":false},{"ty":"tr","p":{"a":0,"k":[139.115,155.524],"ix":2},"a":{"a":0,"k":[0,0],"ix":1},"s":{"a":0,"k":[100,100],"ix":3},"r":{"a":0,"k":0,"ix":6},"o":{"a":0,"k":100,"ix":7},"sk":{"a":0,"k":0,"ix":4},"sa":{"a":0,"k":0,"ix":5},"nm":"Transformieren"}],"nm":"Gruppe 10","np":2,"cix":2,"bm":0,"ix":10,"mn":"ADBE Vector Group","hd":false},{"ty":"gr","it":[{"ind":0,"ty":"sh","ix":1,"ks":{"a":0,"k":{"i":[[0,0],[-3.509,-3.165],[0,0],[-4.048,0],[0,0],[-3.095,3.19],[0,0],[-0.058,4.413],[0,0],[0,0],[9.151,0],[0,0],[0,-9.348],[0,0]],"o":[[0.064,4.774],[0,0],[3.035,2.738],[0,0],[4.397,0],[0,0],[3.048,-3.141],[0,0],[0,0],[0,-9.348],[0,0],[-9.151,0],[0,0],[0,0]],"v":[[-125.147,80.854],[-119.537,93.328],[-63.48,143.895],[-52.495,148.141],[60.348,148.141],[72.137,143.121],[120.341,93.426],[125.148,81.725],[104.62,-130.941],[104.62,-131.189],[88.024,-148.141],[-88.023,-148.141],[-104.619,-131.189],[-104.644,-130.694]],"c":true},"ix":2},"nm":"Pfad 1","mn":"ADBE Vector Shape - Group","hd":false},{"ind":1,"ty":"sh","ix":2,"ks":{"a":0,"k":{"i":[[7.157,0],[0,0],[4.923,4.442],[0,0],[0,7.759],[0,0],[0,0],[-14.725,0],[0,0],[-0.138,-14.888],[0,0],[0,0],[4.968,-5.122],[0,0]],"o":[[0,0],[-6.593,0],[0,0],[-5.72,-5.16],[0,0],[0,0],[0.138,-14.887],[0,0],[14.725,0],[0,0],[0,0],[0,7.182],[0,0],[-5.017,5.172]],"v":[[60.348,158.405],[-52.495,158.405],[-70.354,151.516],[-126.412,100.951],[-135.412,80.623],[-135.388,80.128],[-114.882,-131.449],[-88.023,-158.405],[88.024,-158.405],[114.883,-131.448],[135.412,81.247],[135.412,81.493],[127.708,100.572],[79.504,150.266]],"c":true},"ix":2},"nm":"Pfad 2","mn":"ADBE Vector Shape - Group","hd":false},{"ty":"mm","mm":1,"nm":"Pfade zusammenführen 1","mn":"ADBE Vector Filter - Merge","hd":false},{"ty":"fl","c":{"a":0,"k":[0.988235353956,0.980392216701,0.945098099054,1],"ix":4},"o":{"a":0,"k":100,"ix":5},"r":1,"bm":0,"nm":"Fläche 1","mn":"ADBE Vector Graphic - Fill","hd":false},{"ty":"tr","p":{"a":0,"k":[138.315,158.655],"ix":2},"a":{"a":0,"k":[0,0],"ix":1},"s":{"a":0,"k":[100,100],"ix":3},"r":{"a":0,"k":0,"ix":6},"o":{"a":0,"k":100,"ix":7},"sk":{"a":0,"k":0,"ix":4},"sa":{"a":0,"k":0,"ix":5},"nm":"Transformieren"}],"nm":"Gruppe 11","np":4,"cix":2,"bm":0,"ix":11,"mn":"ADBE Vector Group","hd":false},{"ty":"gr","it":[{"ind":0,"ty":"sh","ix":1,"ks":{"a":0,"k":{"i":[[-2.688,-2.546],[0,0],[-3.084,0],[0,0],[-2.414,2.576],[0,0],[0,0],[-0.064,3.496],[0,0],[0,0],[7.052,0],[0,0],[0,-7.564],[0,0],[0,0]],"o":[[0,0],[2.328,2.174],[0,0],[3.401,0],[0,0],[0,0],[2.298,-2.49],[0,0],[0,0],[0,-7.564],[0,0],[-7.051,0],[0,0],[0,0],[0.069,3.836]],"v":[[-97.995,81.871],[-51.691,121.671],[-43.297,125.042],[49.773,125.042],[58.79,121.048],[58.941,120.895],[98.615,81.987],[102.317,72.6],[81.791,-111.038],[81.791,-111.324],[69.002,-125.041],[-69.004,-125.041],[-81.792,-111.324],[-81.825,-110.752],[-102.319,71.858]],"c":true},"ix":2},"nm":"Pfad 1","mn":"ADBE Vector Shape - Group","hd":false},{"ind":1,"ty":"sh","ix":2,"ks":{"a":0,"k":{"i":[[6.14,0],[0,0],[4.225,3.906],[0,0],[0,6.801],[0,0],[0,0],[-12.614,0],[0,0],[-0.156,-13.084],[0,0],[0,0],[4.222,-4.504],[0,0],[0,0]],"o":[[0,0],[-5.657,0],[0,0],[-4.866,-4.542],[0,0],[0,0],[0.155,-13.083],[0,0],[12.615,0],[0,0],[0,0],[0,6.293],[0,0],[0,0],[-4.306,4.547]],"v":[[49.773,135.305],[-43.297,135.305],[-58.613,129.25],[-104.929,89.441],[-112.585,71.593],[-112.553,71.02],[-92.054,-111.628],[-69.004,-135.305],[69.002,-135.305],[92.053,-111.626],[112.584,72.05],[112.584,72.336],[106.036,89.079],[105.885,89.233],[66.199,128.152]],"c":true},"ix":2},"nm":"Pfad 2","mn":"ADBE Vector Shape - Group","hd":false},{"ty":"mm","mm":1,"nm":"Pfade zusammenführen 1","mn":"ADBE Vector Filter - Merge","hd":false},{"ty":"fl","c":{"a":0,"k":[0.988235353956,0.980392216701,0.945098099054,1],"ix":4},"o":{"a":0,"k":100,"ix":5},"r":1,"bm":0,"nm":"Fläche 1","mn":"ADBE Vector Graphic - Fill","hd":false},{"ty":"tr","p":{"a":0,"k":[138.316,160.022],"ix":2},"a":{"a":0,"k":[0,0],"ix":1},"s":{"a":0,"k":[100,100],"ix":3},"r":{"a":0,"k":0,"ix":6},"o":{"a":0,"k":100,"ix":7},"sk":{"a":0,"k":0,"ix":4},"sa":{"a":0,"k":0,"ix":5},"nm":"Transformieren"}],"nm":"Gruppe 12","np":4,"cix":2,"bm":0,"ix":12,"mn":"ADBE Vector Group","hd":false},{"ty":"gr","it":[{"ind":0,"ty":"sh","ix":1,"ks":{"a":0,"k":{"i":[[23.011,0.92],[-23.011,0.327],[-11.505,0.121],[0,0],[0,0],[-11.505,-0.207],[-23.011,-0.926],[23.011,-0.325],[11.505,-0.124],[0,0],[0,0],[11.505,0.205]],"o":[[23.011,-0.92],[11.505,-0.205],[0,0],[0,0],[11.505,0.124],[23.011,0.325],[-23.011,0.926],[-11.505,0.207],[0,0],[0,0],[-11.505,-0.121],[-23.011,-0.327]],"v":[[-138.065,0],[-69.032,-1.729],[-34.516,-2.1],[0.001,-2.222],[34.516,-2.106],[69.033,-1.735],[138.065,0],[69.033,1.735],[34.516,2.106],[0.001,2.222],[-34.516,2.1],[-69.032,1.729]],"c":true},"ix":2},"nm":"Pfad 1","mn":"ADBE Vector Shape - Group","hd":false},{"ty":"fl","c":{"a":0,"k":[0.988235353956,0.980392216701,0.945098099054,1],"ix":4},"o":{"a":0,"k":100,"ix":5},"r":1,"bm":0,"nm":"Fläche 1","mn":"ADBE Vector Graphic - Fill","hd":false},{"ty":"tr","p":{"a":0,"k":[138.315,442.194],"ix":2},"a":{"a":0,"k":[0,0],"ix":1},"s":{"a":0,"k":[100,100],"ix":3},"r":{"a":0,"k":0,"ix":6},"o":{"a":0,"k":100,"ix":7},"sk":{"a":0,"k":0,"ix":4},"sa":{"a":0,"k":0,"ix":5},"nm":"Transformieren"}],"nm":"Gruppe 13","np":2,"cix":2,"bm":0,"ix":13,"mn":"ADBE Vector Group","hd":false},{"ty":"gr","it":[{"ind":0,"ty":"sh","ix":1,"ks":{"a":0,"k":{"i":[[0,-2.49],[0.631,-1.989],[1.035,-1.519],[1.39,-1.068],[1.488,-0.678],[1.536,-0.323],[1.358,0],[0,0],[0,0],[0,0],[-1.343,1.424],[0,2.395],[0.356,0.97],[0.663,0.711],[0.954,0.389],[1.164,0],[0,0],[2.36,0.728],[2.022,1.617],[1.342,2.621],[0,3.786],[-1.343,2.605],[-2.022,1.634],[-2.363,0.728],[-2.038,0],[0,0],[0,0],[0,0],[1.341,-1.455],[0,-2.394],[-1.344,-1.408],[-2.394,0],[0,0],[0,0],[-1.521,-0.339],[-1.505,-0.711],[-1.359,-1.084],[-1.052,-1.521],[-0.615,-1.972]],"o":[[0,2.492],[-0.631,1.99],[-1.036,1.521],[-1.391,1.068],[-1.489,0.679],[-1.537,0.324],[0,0],[0,0],[0,0],[2.426,0],[1.342,-1.424],[0,-1.164],[-0.356,-0.97],[-0.664,-0.713],[-0.954,-0.387],[0,0],[-2.038,0],[-2.363,-0.727],[-2.022,-1.617],[-1.343,-2.621],[0,-3.785],[1.342,-2.604],[2.022,-1.633],[2.36,-0.727],[0,0],[0,0],[0,0],[-2.394,0],[-1.344,1.457],[0,2.427],[1.341,1.407],[0,0],[0,0],[1.359,0.032],[1.521,0.34],[1.504,0.713],[1.358,1.083],[1.051,1.521],[0.614,1.974]],"v":[[34.77,14.315],[33.824,21.036],[31.325,26.302],[27.685,30.185],[23.366,32.805],[18.829,34.31],[14.486,34.794],[-34.188,34.794],[-34.188,22.178],[14.486,22.178],[20.139,20.043],[22.153,14.315],[21.619,11.114],[20.091,8.591],[17.664,6.94],[14.486,6.358],[-14.534,6.358],[-21.133,5.266],[-27.709,1.747],[-32.756,-4.609],[-34.77,-14.219],[-32.756,-23.802],[-27.709,-30.159],[-21.133,-33.702],[-14.534,-34.794],[28.413,-34.794],[28.413,-22.177],[-14.534,-22.177],[-20.138,-19.993],[-22.152,-14.219],[-20.138,-8.467],[-14.534,-6.357],[14.486,-6.357],[14.583,-6.357],[18.901,-5.799],[23.439,-4.222],[27.734,-1.527],[31.349,2.379],[33.848,7.618]],"c":true},"ix":2},"nm":"Pfad 1","mn":"ADBE Vector Shape - Group","hd":false},{"ty":"fl","c":{"a":0,"k":[0.988235353956,0.980392216701,0.945098099054,1],"ix":4},"o":{"a":0,"k":100,"ix":5},"r":1,"bm":0,"nm":"Fläche 1","mn":"ADBE Vector Graphic - Fill","hd":false},{"ty":"tr","p":{"a":0,"k":[220.885,385.843],"ix":2},"a":{"a":0,"k":[0,0],"ix":1},"s":{"a":0,"k":[100,100],"ix":3},"r":{"a":0,"k":0,"ix":6},"o":{"a":0,"k":100,"ix":7},"sk":{"a":0,"k":0,"ix":4},"sa":{"a":0,"k":0,"ix":5},"nm":"Transformieren"}],"nm":"Gruppe 14","np":2,"cix":2,"bm":0,"ix":14,"mn":"ADBE Vector Group","hd":false},{"ty":"gr","it":[{"ind":0,"ty":"sh","ix":1,"ks":{"a":0,"k":{"i":[[0,0],[0,0],[0,0],[0,0],[0,0],[0,0],[0,0],[0,0]],"o":[[0,0],[0,0],[0,0],[0,0],[0,0],[0,0],[0,0],[0,0]],"v":[[34.139,-22.178],[6.333,-22.178],[6.333,34.794],[-6.285,34.794],[-6.285,-22.178],[-34.139,-22.178],[-34.139,-34.794],[34.139,-34.794]],"c":true},"ix":2},"nm":"Pfad 1","mn":"ADBE Vector Shape - Group","hd":false},{"ty":"fl","c":{"a":0,"k":[0.988235353956,0.980392216701,0.945098099054,1],"ix":4},"o":{"a":0,"k":100,"ix":5},"r":1,"bm":0,"nm":"Fläche 1","mn":"ADBE Vector Graphic - Fill","hd":false},{"ty":"tr","p":{"a":0,"k":[145.376,385.843],"ix":2},"a":{"a":0,"k":[0,0],"ix":1},"s":{"a":0,"k":[100,100],"ix":3},"r":{"a":0,"k":0,"ix":6},"o":{"a":0,"k":100,"ix":7},"sk":{"a":0,"k":0,"ix":4},"sa":{"a":0,"k":0,"ix":5},"nm":"Transformieren"}],"nm":"Gruppe 15","np":2,"cix":2,"bm":0,"ix":15,"mn":"ADBE Vector Group","hd":false},{"ty":"gr","it":[{"ind":0,"ty":"sh","ix":1,"ks":{"a":0,"k":{"i":[[0,0],[0,0],[0,0],[0,0],[0.986,-0.517],[1.132,0],[0.954,0.517],[0.55,1.003],[0,0],[0,0],[0,0],[0,0],[-0.858,1.133],[-1.392,0.389],[-0.68,-0.048],[-0.631,-0.244],[-0.517,-0.437],[-0.356,-0.614],[0,0],[0,0],[-1.31,0.517],[-1.424,-0.355],[-0.874,-1.132],[0,-1.457]],"o":[[0,0],[0,0],[0,0],[-0.551,1.003],[-0.988,0.517],[-1.1,0],[-0.955,-0.517],[0,0],[0,0],[0,0],[0,0],[0,-1.457],[0.857,-1.132],[0.679,-0.161],[0.679,0.049],[0.631,0.243],[0.518,0.436],[0,0],[0,0],[0.745,-1.229],[1.31,-0.518],[1.358,0.389],[0.874,1.133],[0,0]],"v":[[40.496,34.876],[27.782,34.876],[27.782,-6.568],[5.411,32.789],[3.106,35.069],[-0.073,35.845],[-3.154,35.069],[-5.411,32.789],[-27.879,-6.568],[-27.879,34.876],[-40.496,34.876],[-40.496,-29.327],[-39.21,-33.208],[-35.837,-35.491],[-33.799,-35.66],[-31.834,-35.223],[-30.112,-34.203],[-28.801,-32.626],[-0.073,17.309],[28.655,-32.626],[31.737,-35.246],[35.838,-35.491],[39.186,-33.208],[40.496,-29.327]],"c":true},"ix":2},"nm":"Pfad 1","mn":"ADBE Vector Shape - Group","hd":false},{"ty":"fl","c":{"a":0,"k":[0.988235353956,0.980392216701,0.945098099054,1],"ix":4},"o":{"a":0,"k":100,"ix":5},"r":1,"bm":0,"nm":"Fläche 1","mn":"ADBE Vector Graphic - Fill","hd":false},{"ty":"tr","p":{"a":0,"k":[61.472,385.762],"ix":2},"a":{"a":0,"k":[0,0],"ix":1},"s":{"a":0,"k":[100,100],"ix":3},"r":{"a":0,"k":0,"ix":6},"o":{"a":0,"k":100,"ix":7},"sk":{"a":0,"k":0,"ix":4},"sa":{"a":0,"k":0,"ix":5},"nm":"Transformieren"}],"nm":"Gruppe 16","np":2,"cix":2,"bm":0,"ix":16,"mn":"ADBE Vector Group","hd":false}],"ip":0,"op":600,"st":0,"bm":0}],"markers":[]}